closed_caption/__init__.py
closed_caption/cli.py
closed_caption/generate.py
closed_caption-1.0.1.dist-info/LICENSE
closed_caption-1.0.1.dist-info/METADATA
closed_caption-1.0.1.dist-info/WHEEL
closed_caption-1.0.1.dist-info/entry_points.txt
closed_caption-1.0.1.dist-info/top_level.txt
closed_caption-1.0.1.dist-info/RECORD
