Metadata-Version: 2.1
Name: closed-caption
Version: 1.0.1
Summary: Tạo phụ đề từ video sử dụng OpenAI Whisper.
Home-page: https://github.com/haiphamcoder/closed-caption
Author: Phạm Ngọc Hải
Author-email: ngochai285nd@gmail.com
License: UNKNOWN
Platform: UNKNOWN
Classifier: Programming Language :: Python :: 3
Classifier: License :: OSI Approved :: MIT License
Classifier: Operating System :: OS Independent
Requires-Python: >=3.7
Requires-Dist: pysrt>=1.1.2
Requires-Dist: openai-whisper>=0.1.0
